relay_bp-0.2.0.dist-info/METADATA
relay_bp-0.2.0.dist-info/WHEEL
relay_bp-0.2.0.dist-info/licenses/LICENSE.txt
relay_bp/__init__.py
relay_bp/bp/__init__.py
relay_bp/decoder.py
relay_bp/observable_decoder.py
relay_bp/stim/__init__.py
relay_bp/stim/noise.py
relay_bp/stim/sinter/__init__.py
relay_bp/stim/sinter/check_matrices.py
relay_bp/stim/sinter/decoders.py
relay_bp/stim/sinter/utils.py
_relay_bp/__init__.py
_relay_bp/_relay_bp.cpython-313-x86_64-linux-gnu.so
relay_bp-0.2.0.dist-info/RECORD
